RainyLibrary/RainyAppCommon.robot
RainyLibrary/RainyCommon.robot
RainyLibrary/RainyWebCommon.robot
RainyLibrary/__init__.py
RainyLibrary/imports.robot
RainyLibrary/version.py
RainyLibrary/utils/AdbUtils.py
RainyLibrary/utils/AppiumUtils.py
RainyLibrary/utils/DateUtils.py
RainyLibrary/utils/GeneralUtils.py
RainyLibrary/utils/ImageUtils.py
RainyLibrary/utils/JsonUtils.py
RainyLibrary/utils/__init__.py
robotframework_RainyLibrary-1.0.2.dist-info/LICENSE
robotframework_RainyLibrary-1.0.2.dist-info/METADATA
robotframework_RainyLibrary-1.0.2.dist-info/WHEEL
robotframework_RainyLibrary-1.0.2.dist-info/top_level.txt
robotframework_RainyLibrary-1.0.2.dist-info/RECORD
