Metadata-Version: 2.1
Name: robotframework-RainyLibrary
Version: 1.0.2
Summary: rainy common library for robot framework
Home-page: https://gitlab.com/wpchagorn24/robotframework-rainylibrary
Author: watchagorn pattummee
Author-email: wpchagorn24@gmail.com
Keywords: RainyWebCommon,RainyCommon,RainyAppCommon,RainyLibrary
Classifier: Programming Language :: Python
Classifier: Programming Language :: Python :: 2
Classifier: Programming Language :: Python :: 3
Classifier: License :: OSI Approved :: MIT License
Classifier: Operating System :: OS Independent
Classifier: Framework :: Robot Framework
Classifier: Framework :: Robot Framework :: Library
License-File: LICENSE
Requires-Dist: robotframework (==7.1)
Requires-Dist: robotframework-browsermobproxylibrary (==0.1.3)
Requires-Dist: robotframework-browser
Requires-Dist: robotframework-debuglibrary
Requires-Dist: robotframework-databaselibrary
Requires-Dist: robotframework-datadriver
Requires-Dist: robotframework-datetime-tz
Requires-Dist: robotframework-faker
Requires-Dist: robotframework-seleniumlibrary
Requires-Dist: robotframework-seleniumtestability
Requires-Dist: robotframework-pdf2textlibrary
Requires-Dist: robotframework-pabot
Requires-Dist: robotframework-requests
Requires-Dist: robotframework-sshlibrary
Requires-Dist: robotframework-robocop
Requires-Dist: robotframework-jsonlibrary
Requires-Dist: robotframework-imaplibrary2
Requires-Dist: robotframework-excellib
Requires-Dist: robotframework-appiumlibrary
Requires-Dist: robotframework-csvlibrary
Requires-Dist: RESTinstance
Requires-Dist: jsonpath2
Requires-Dist: pyzxing
Requires-Dist: PyMySQL
Requires-Dist: PyYAML
Requires-Dist: DateTime
Requires-Dist: openpyxl
Requires-Dist: certifi
Requires-Dist: cx-Oracle
Requires-Dist: opencv-python
Requires-Dist: PyPDF2
